tests/__init__.py
tests/conftest.py
tests/test_proxypool.py
tests/test_websvr.py
zwpool/__init__.py
zwpool/__version__.py
zwpool/websvr.py
zwpool/proxy/__init__.py
zwpool/proxy/freeproxy.py
zwpool/proxy/proxypool.py
zwpool-0.0.2.dist-info/LICENSE
zwpool-0.0.2.dist-info/METADATA
zwpool-0.0.2.dist-info/WHEEL
zwpool-0.0.2.dist-info/top_level.txt
zwpool-0.0.2.dist-info/RECORD
