Metadata-Version: 2.1
Name: zwpool
Version: 0.0.2
Summary: Personal Pool utils.
Home-page: https://github.com/njzhaowei/zwpool
Author: Zhao Wei
Author-email: yewberry@163.com
License: Apache 2.0
Platform: all
Classifier: Programming Language :: Python :: 3
Classifier: License :: OSI Approved :: Apache Software License
Classifier: Operating System :: OS Independent
Requires-Python: >=3.6
Requires-Dist: zwutils
Requires-Dist: zwdb
Requires-Dist: requests
Requires-Dist: beautifulsoup4
Requires-Dist: web.py
